eastmoney/__init__.py
eastmoney/__main__.py
eastmoney/eastmoney.py
eastmoney/f10.py
tests/__init__.py
tests/test_f10.py
pyeastmoney-0.1.0.dist-info/METADATA
pyeastmoney-0.1.0.dist-info/WHEEL
pyeastmoney-0.1.0.dist-info/top_level.txt
pyeastmoney-0.1.0.dist-info/RECORD
