Metadata-Version: 2.1
Name: pyeastmoney
Version: 0.1.0
Summary: 获取东方财富数据。
Home-page: https://github.com/songjian/pyeastmoney
Author: sj
Author-email: 724385768@qq.com
License: UNKNOWN
Platform: UNKNOWN
Classifier: Programming Language :: Python :: 3
Classifier: License :: OSI Approved :: MIT License
Classifier: Operating System :: OS Independent
Requires-Python: >=3
Requires-Dist: beautifulsoup4 (==4.10.0)
Requires-Dist: pandas (==1.3.5)
Requires-Dist: requests (==2.30.0)
Requires-Dist: tqdm (==4.65.0)
